apyefa/__init__.py
apyefa/client.py
apyefa/data_classes.py
apyefa/exceptions.py
apyefa/helpers.py
apyefa/commands/__init__.py
apyefa/commands/command.py
apyefa/commands/command_add_info.py
apyefa/commands/command_coord.py
apyefa/commands/command_departures.py
apyefa/commands/command_geoobject.py
apyefa/commands/command_line_list.py
apyefa/commands/command_line_stop.py
apyefa/commands/command_serving_lines.py
apyefa/commands/command_stop_finder.py
apyefa/commands/command_stop_list.py
apyefa/commands/command_system_info.py
apyefa/commands/command_trip.py
apyefa/commands/parsers/__init__.py
apyefa/commands/parsers/parser.py
apyefa/commands/parsers/rapid_json_parser.py
apyefa/commands/parsers/xml_parser.py
apyefa-1.1.7.dist-info/licenses/LICENSE
apyefa-1.1.7.dist-info/METADATA
apyefa-1.1.7.dist-info/WHEEL
apyefa-1.1.7.dist-info/top_level.txt
apyefa-1.1.7.dist-info/RECORD
