Metadata-Version: 2.4
Name: apyefa
Version: 1.1.7
Summary: Python API for EFA(Elektronische Fahrplanauskunft) async requests
Author-email: Alex Jung <jungdevelop@gmail.com>
Project-URL: Homepage, https://github.com/alex-jung/apyefa
Project-URL: Documentation, https://github.com/alex-jung/apyefa
Project-URL: Repository, https://github.com/alex-jung/apyefa
Project-URL: Issues, https://github.com/alex-jung/apyefa/issues
Keywords: efa,public transport,traffic
Requires-Python: >=3.11
License-File: LICENSE
Requires-Dist: aiohttp>=3.11.2
Requires-Dist: voluptuous>=0.15.2
Requires-Dist: tzdata>=2024.2
Requires-Dist: black>=25.12.0
Requires-Dist: twine>=6.2.0
Dynamic: license-file
